qibolab_qblox/__init__.py
qibolab_qblox-0.0.3.dist-info/LICENSE
qibolab_qblox-0.0.3.dist-info/METADATA
qibolab_qblox-0.0.3.dist-info/WHEEL
qibolab_qblox-0.0.3.dist-info/RECORD
