Metadata-Version: 2.3
Name: qibolab-qblox
Version: 0.0.3
Summary: Quantum hardware module and drivers for Qibo
License: Apache-2.0
Author: The Qibo team
Requires-Python: >=3.10,<3.14
Classifier: License :: OSI Approved :: Apache Software License
Classifier: Programming Language :: Python :: 3
Classifier: Programming Language :: Python :: 3.10
Classifier: Programming Language :: Python :: 3.11
Classifier: Programming Language :: Python :: 3.12
Classifier: Programming Language :: Python :: 3.13
Classifier: Topic :: Scientific/Engineering :: Physics
Requires-Dist: lark (>=1.1.9,<2.0.0)
Requires-Dist: pyvisa-py (>=0.8.0,<0.9.0)
Requires-Dist: qblox-instruments (==0.16.0)
Requires-Dist: qcodes (>=0.52.0,<0.53.0)
Requires-Dist: qcodes_contrib_drivers (>=0.23.0,<0.24.0)
Requires-Dist: qibolab (>=0.2.8,<0.3.0)
Project-URL: Documentation, https://qibo.science/docs/qibolab-qblox/stable
Project-URL: Homepage, https://qibo.science/
Project-URL: Repository, https://github.com/qiboteam/qibolab-qblox/
